MANIFEST.in
README.rst
setup.cfg
setup.py
lava/__init__.py
lava/raven/__init__.py
lava/raven/extension.py
lava_raven.egg-info/PKG-INFO
lava_raven.egg-info/SOURCES.txt
lava_raven.egg-info/dependency_links.txt
lava_raven.egg-info/entry_points.txt
lava_raven.egg-info/namespace_packages.txt
lava_raven.egg-info/requires.txt
lava_raven.egg-info/top_level.txt
lava_raven.egg-info/zip-safe