Metadata-Version: 1.0
Name: lava-raven
Version: 0.1.1
Summary: Raven/Sentry support for LAVA Server
Home-page: https://launchpad.net/lava-raven
Author: Zygmunt Krynicki
Author-email: zygmunt.krynicki@linaro.org
License: LGPL
Platform: UNKNOWN
Classifier: Development Status :: 4 - Beta
Classifier: Intended Audience :: Developers
Classifier: License :: OSI Approved :: GNU Library or Lesser General Public License (LGPL)
Classifier: Operating System :: OS Independent
Classifier: Programming Language :: Python :: 2.6
Classifier: Programming Language :: Python :: 2.7
Classifier: Topic :: Software Development :: Testing
